{
  "usdt": 175431.92,
  "equity": 175201.34,
  "unrealised": -230.58,
  "assets": [
    {
      "asset": "BTC",
      "free": "100.016597",
      "total": "100.02"
    },
    {
      "asset": "ETH",
      "free": "1000.941004",
      "total": "1000.94"
    },
    {
      "asset": "USDC",
      "free": "73654.022474",
      "total": "74330.96"
    },
    {
      "asset": "USDT",
      "free": "100000.0",
      "total": "100000.0"
    }
  ],
  "updated_at": "2026-06-27 05:42 UTC",
  "mode": "deribit_testnet",
  "exchange": "Deribit(by Coinbase) Testnet",
  "open_positions": 5
}