{
  "usdt": 174665.39,
  "equity": 174631.68,
  "unrealised": -33.7113,
  "assets": [
    {
      "asset": "BTC",
      "free": "100.016597",
      "total": "100.02"
    },
    {
      "asset": "ETH",
      "free": "1000.941004",
      "total": "1000.94"
    },
    {
      "asset": "USDC",
      "free": "72854.798415",
      "total": "73564.14"
    },
    {
      "asset": "USDT",
      "free": "100000.0",
      "total": "100000.0"
    }
  ],
  "updated_at": "2026-05-03 17:52 UTC",
  "mode": "deribit_testnet",
  "exchange": "Deribit(by Coinbase) Testnet",
  "open_positions": 5
}