{
  "usdt": 174993.03,
  "equity": 175549.41,
  "unrealised": 556.3789,
  "assets": [
    {
      "asset": "BTC",
      "free": "100.016597",
      "total": "100.02"
    },
    {
      "asset": "ETH",
      "free": "1000.941004",
      "total": "1000.94"
    },
    {
      "asset": "USDC",
      "free": "72328.828331",
      "total": "73892.07"
    },
    {
      "asset": "USDT",
      "free": "100000.0",
      "total": "100000.0"
    }
  ],
  "updated_at": "2026-05-01 16:14 UTC",
  "mode": "deribit_testnet",
  "exchange": "Deribit(by Coinbase) Testnet",
  "open_positions": 4
}