{
  "usdt": 173347.33,
  "equity": 173362.16,
  "unrealised": 14.8273,
  "assets": [
    {
      "asset": "BTC",
      "free": "100.016597",
      "total": "100.02"
    },
    {
      "asset": "ETH",
      "free": "1000.941004",
      "total": "1000.94"
    },
    {
      "asset": "USDC",
      "free": "71878.184642",
      "total": "72246.37"
    },
    {
      "asset": "USDT",
      "free": "100000.0",
      "total": "100000.0"
    }
  ],
  "updated_at": "2026-05-06 16:56 UTC",
  "mode": "deribit_testnet",
  "exchange": "Deribit(by Coinbase) Testnet",
  "open_positions": 2
}