{
  "usdt": 173874.47,
  "equity": 173946.48,
  "unrealised": 72.0126,
  "assets": [
    {
      "asset": "BTC",
      "free": "100.016597",
      "total": "100.02"
    },
    {
      "asset": "ETH",
      "free": "1000.941004",
      "total": "1000.94"
    },
    {
      "asset": "USDC",
      "free": "70374.112094",
      "total": "72773.51"
    },
    {
      "asset": "USDT",
      "free": "100000.0",
      "total": "100000.0"
    }
  ],
  "updated_at": "2026-07-22 21:34 UTC",
  "mode": "deribit_testnet",
  "exchange": "Deribit(by Coinbase) Testnet",
  "open_positions": 5
}