{
  "accuracy": 59.2,
  "cv_mean": 58.2,
  "cv_std": 0.2,
  "n_train": 19084,
  "n_test": 4772,
  "features": [
    "ema9",
    "ema20",
    "ema50",
    "ema200",
    "ema20_slope",
    "ema50_slope",
    "price_vs_ema20",
    "price_vs_ema50",
    "price_vs_ema200",
    "ema20_vs_ema50",
    "rsi",
    "rsi_slope",
    "rsi_fast",
    "stoch_k",
    "stoch_d",
    "macd",
    "macd_signal",
    "macd_hist",
    "macd_slope",
    "adx",
    "adx_pos",
    "adx_neg",
    "di_diff",
    "atr",
    "atr_pct",
    "bb_high",
    "bb_low",
    "bb_pct",
    "bb_width",
    "volume_ratio",
    "volume_spike",
    "obv_slope",
    "price_change",
    "price_change3",
    "price_change6",
    "high_low_pct",
    "body_pct",
    "momentum",
    "volatility",
    "bullish_candle",
    "doji",
    "hammer",
    "rsi_1h",
    "adx_1h",
    "trend_1h"
  ],
  "selected": [
    "volume_ratio",
    "volume_spike",
    "obv_slope",
    "bb_width",
    "atr_pct",
    "volatility",
    "bb_low",
    "ema20",
    "bb_high",
    "price_vs_ema20",
    "ema200",
    "rsi_1h",
    "price_vs_ema200",
    "ema50",
    "ema20_vs_ema50",
    "macd_signal",
    "adx",
    "adx_1h",
    "macd_hist",
    "stoch_d",
    "price_change6",
    "atr",
    "macd",
    "di_diff",
    "momentum",
    "price_vs_ema50",
    "ema9",
    "rsi_fast",
    "price_change3",
    "adx_pos",
    "doji",
    "ema50_slope"
  ],
  "target_pct": 0.003,
  "n_symbols": 24,
  "recommended_threshold": 0.45,
  "buy_precision": 62.8,
  "buy_recall": 56.6,
  "sell_precision": 62.7,
  "sell_recall": 56.8
}