{
  "accuracy": 54.0,
  "wf_mean": 44.8,
  "wf_std": 4.2,
  "n_train": 270954,
  "n_calib": 62614,
  "n_train_sampled": 257486,
  "n_test": 83486,
  "features": [
    "ema9",
    "ema20",
    "ema50",
    "ema200",
    "ema20_slope",
    "ema50_slope",
    "price_vs_ema20",
    "price_vs_ema50",
    "price_vs_ema200",
    "ema20_vs_ema50",
    "rsi",
    "rsi_slope",
    "rsi_fast",
    "stoch_k",
    "stoch_d",
    "macd",
    "macd_signal",
    "macd_hist",
    "macd_slope",
    "adx",
    "adx_pos",
    "adx_neg",
    "di_diff",
    "atr",
    "atr_pct",
    "bb_high",
    "bb_low",
    "bb_pct",
    "bb_width",
    "volume_ratio",
    "volume_spike",
    "obv_slope",
    "vwap_dev",
    "price_change",
    "price_change3",
    "price_change6",
    "high_low_pct",
    "body_pct",
    "momentum",
    "volatility",
    "pivot_dev",
    "bullish_candle",
    "doji",
    "hammer",
    "rsi_1h",
    "adx_1h",
    "trend_1h",
    "rsi_4h",
    "trend_4h",
    "vol_regime",
    "taker_buy_ratio",
    "hour_sin",
    "hour_cos",
    "dow_sin",
    "dow_cos",
    "btc_corr_20",
    "btc_beta_20",
    "btc_rel_strength"
  ],
  "selected": [
    "volume_ratio",
    "volume_spike",
    "obv_slope",
    "bb_width",
    "atr_pct",
    "volatility",
    "vwap_dev",
    "rsi_4h",
    "trend_1h",
    "dow_sin",
    "dow_cos",
    "price_vs_ema200",
    "trend_4h",
    "hour_sin",
    "rsi_1h",
    "hour_cos",
    "ema50",
    "ema20_vs_ema50",
    "ema200",
    "bb_high",
    "vol_regime",
    "adx_1h",
    "price_vs_ema50",
    "btc_beta_20",
    "bb_low",
    "btc_corr_20",
    "macd_signal",
    "ema20",
    "adx",
    "ema50_slope",
    "atr",
    "rsi",
    "ema9",
    "macd",
    "ema20_slope"
  ],
  "buy_precision": 0.4662,
  "sell_precision": 0.4516,
  "buy_recall": 0.1328,
  "sell_recall": 0.1042
}